pygds/__init__.py
pygds/algorithms.py
pygds/gds.py
pygds/graph.py
pygds/mixins.py
pygds-0.2.0.dist-info/LICENSE
pygds-0.2.0.dist-info/METADATA
pygds-0.2.0.dist-info/WHEEL
pygds-0.2.0.dist-info/top_level.txt
pygds-0.2.0.dist-info/RECORD
