Metadata-Version: 2.1
Name: pygds
Version: 0.2.0
Summary: A python wrapper around the Neo4j Graph Data Science Library
Home-page: https://github.com/stellasia/pygds
Author: Estelle Scifo
License: UNKNOWN
Platform: UNKNOWN
Requires-Python: >=3.6
Requires-Dist: neo4j
